fetquest/__init__.py
fetquest/stock_return.py
fetquest-0.0.7.dist-info/LICENSE
fetquest-0.0.7.dist-info/METADATA
fetquest-0.0.7.dist-info/WHEEL
fetquest-0.0.7.dist-info/top_level.txt
fetquest-0.0.7.dist-info/RECORD
