Metadata-Version: 2.1
Name: fetquest
Version: 0.0.7
Summary: Package to help on Stock Market Visualization and Data
Author: Dhinesh Palanisamy
Author-email: daps.investment@gmail.com
License-File: LICENSE
Requires-Dist: yfinance
Requires-Dist: pandas
Requires-Dist: plotly.express
